cucutags.py
cucutags-0.7.4.dist-info/DESCRIPTION.rst
cucutags-0.7.4.dist-info/METADATA
cucutags-0.7.4.dist-info/RECORD
cucutags-0.7.4.dist-info/WHEEL
cucutags-0.7.4.dist-info/metadata.json
cucutags-0.7.4.dist-info/top_level.txt
